gaboon/__init__.py
gaboon-0.1.dist-info/LICENSE
gaboon-0.1.dist-info/METADATA
gaboon-0.1.dist-info/WHEEL
gaboon-0.1.dist-info/top_level.txt
gaboon-0.1.dist-info/RECORD
