Metadata-Version: 2.1
Name: gaboon
Version: 0.1
Summary: A collection of Algorithms
Home-page: https://github.com/betaoverflow/gaboon
Author: Aniket Pal
Author-email: aniketindian8@gmail.com
License: UNKNOWN
Platform: UNKNOWN
Classifier: Programming Language :: Python :: 3
Classifier: License :: OSI Approved :: MIT License
Classifier: Operating System :: OS Independent
